lightorch/__init__.py
lightorch/_version.py
lightorch/antique.py
lightorch/hparams.py
lightorch/nn/__init__.py
lightorch/nn/complex.py
lightorch/nn/criterions.py
lightorch/nn/dnn.py
lightorch/nn/fourier.py
lightorch/nn/functional.py
lightorch/nn/monte_carlo.py
lightorch/nn/normalization.py
lightorch/nn/partial.py
lightorch/nn/utils.py
lightorch/nn/sequential/__init__.py
lightorch/nn/sequential/residual.py
lightorch/nn/transformer/__init__.py
lightorch/nn/transformer/attention.py
lightorch/nn/transformer/embedding.py
lightorch/nn/transformer/ffn.py
lightorch/nn/transformer/positional.py
lightorch/nn/transformer/transformer.py
lightorch/training/__init__.py
lightorch/training/adversarial.py
lightorch/training/cli.py
lightorch/training/supervised.py
tests/__init__.py
tests/test_nn.py
tests/test_supervised.py
tests/utils.py
lightorch-0.0.6.dist-info/LICENSE
lightorch-0.0.6.dist-info/METADATA
lightorch-0.0.6.dist-info/WHEEL
lightorch-0.0.6.dist-info/top_level.txt
lightorch-0.0.6.dist-info/RECORD
