Metadata-Version: 2.1
Name: lightorch
Version: 0.0.6
Summary: Pytorch & Lightning based framework for research and ml-pipeline automation.
Home-page: https://github.com/Jorgedavyd/LighTorch
Author: Jorge David Enciso Martínez
Author-email: jorged.encyso@gmail.com
License: MIT
Classifier: Development Status :: 4 - Beta
Classifier: Intended Audience :: Developers
Classifier: Intended Audience :: Science/Research
Classifier: License :: OSI Approved :: MIT License
Classifier: Programming Language :: Python :: 3.8
Classifier: Programming Language :: Python :: 3.9
Classifier: Programming Language :: Python :: 3.10
Classifier: Programming Language :: Python :: 3.11
Classifier: Programming Language :: Python :: 3.12
Classifier: Topic :: Scientific/Engineering :: Artificial Intelligence
Classifier: Topic :: Scientific/Engineering :: Information Analysis
Classifier: Topic :: Scientific/Engineering :: Mathematics
Classifier: Topic :: Scientific/Engineering
Classifier: Topic :: Software Development
Classifier: Topic :: Software Development :: Libraries
Classifier: Topic :: Software Development :: Libraries :: Python Modules
License-File: LICENSE
Requires-Dist: lightning
Requires-Dist: torch
Requires-Dist: torchvision
Requires-Dist: optuna
Requires-Dist: tqdm
